<row>
  <table_name>R_SEARCH_FILTER</table_name>
  <model_name>configuration.RSearchFilter</model_name>
  <data>
    <R_SEARCH_FILTER_ID type="int">2</R_SEARCH_FILTER_ID>
    <RESOURCE_ID type="int">42</RESOURCE_ID>
    <QUESTION_ID type="int">2</QUESTION_ID>
    <FIELD_NAME type="str">community</FIELD_NAME>
    <LABEL type="str">Gemeinde</LABEL>
    <QUERY type="str">instance.instance_id in (select instance_location.instance_id from instance_location where instance_location.location_id = ?)</QUERY>
    <WILDCARD type="int">0</WILDCARD>
    <CLASS type="str"></CLASS>
  </data>
</row>

