[
  {
    "fields": {
      "created": "2019-06-08T19:09:17.591Z",
      "instance": 1,
      "invitee": 8,
      "user": 8
    },
    "model": "applicants.applicant",
    "pk": 1
  },
  {
    "fields": {
      "attachment_sections": [
        1
      ],
      "context": {
        "tags": [
          "grundriss-angabe-bodenflaeche-dokument",
          "situationsplan-dokument",
          "grundriss-dokument",
          "schnitt-dokument"
        ]
      },
      "date": "2019-06-08T19:24:36.681Z",
      "digital_signature": 0,
      "group": 6,
      "identifier": null,
      "instance": 1,
      "is_confidential": 0,
      "is_parcel_picture": 0,
      "mime_type": "application/pdf",
      "name": "pdf-test.pdf",
      "path": "attachments/files/1/pdf-test.pdf",
      "question": null,
      "service": null,
      "size": 20597,
      "user": 8
    },
    "model": "document.attachment",
    "pk": 1
  },
  {
    "fields": {
      "creation_date": "2019-06-08T19:09:17.581Z",
      "form": 1,
      "group": 6,
      "identifier": null,
      "instance_state": 1,
      "location": null,
      "modification_date": "2019-06-08T19:09:17.581Z",
      "previous_instance_state": 1,
      "user": 8
    },
    "model": "instance.instance",
    "pk": 1
  },
  {
    "fields": {
      "address": null,
      "city": null,
      "disabled": 0,
      "email": "admin-camac@example.net",
      "language": "en",
      "last_login": "2018-02-23T14:24:06Z",
      "name": "Static",
      "password": "10602b62c0f171f626e3d64046c27567",
      "phone": null,
      "surname": "Administrator",
      "username": "462afaba-aeb7-494a-8596-3497b81ed701",
      "zip": null
    },
    "model": "user.user",
    "pk": 1
  },
  {
    "fields": {
      "address": null,
      "city": null,
      "disabled": 0,
      "email": null,
      "language": "de",
      "last_login": "2018-02-23T08:21:43Z",
      "name": "Gu",
      "password": null,
      "phone": null,
      "surname": "Est",
      "username": "guest",
      "zip": null
    },
    "model": "user.user",
    "pk": 2
  },
  {
    "fields": {
      "address": null,
      "city": null,
      "disabled": 0,
      "email": "email@example.ch",
      "language": "de",
      "last_login": "2018-02-23T14:27:27Z",
      "name": "Er",
      "password": "77b7675371ce6d9548683775a6245837",
      "phone": null,
      "surname": "Us",
      "username": "855a5ba0-cdcc-48d5-ab7c-4fc55cbe0754",
      "zip": null
    },
    "model": "user.user",
    "pk": 8
  },
  {
    "fields": {
      "default_group": 1,
      "group": 1,
      "user": 1
    },
    "model": "user.usergroup",
    "pk": 1
  },
  {
    "fields": {
      "default_group": 1,
      "group": 2,
      "user": 2
    },
    "model": "user.usergroup",
    "pk": 2
  },
  {
    "fields": {
      "default_group": 1,
      "group": 6,
      "user": 8
    },
    "model": "user.usergroup",
    "pk": 20001
  },
  {
    "fields": {
      "default_group": 0,
      "group": 20096,
      "user": 8
    },
    "model": "user.usergroup",
    "pk": 20099
  },
  {
    "fields": {
      "default_group": 0,
      "group": 20098,
      "user": 8
    },
    "model": "user.usergroup",
    "pk": 20100
  },
  {
    "fields": {
      "default_group": 0,
      "group": 20097,
      "user": 8
    },
    "model": "user.usergroup",
    "pk": 20101
  },
  {
    "fields": {
      "default_group": 0,
      "group": 20005,
      "user": 8
    },
    "model": "user.usergroup",
    "pk": 20102
  },
  {
    "fields": {
      "default_group": 0,
      "group": 20004,
      "user": 8
    },
    "model": "user.usergroup",
    "pk": 20103
  },
  {
    "fields": {
      "default_group": 0,
      "group": 20069,
      "user": 8
    },
    "model": "user.usergroup",
    "pk": 20104
  },
  {
    "fields": {
      "default_group": 0,
      "group": 20009,
      "user": 8
    },
    "model": "user.usergroup",
    "pk": 20106
  },
  {
    "fields": {
      "default_group": 0,
      "group": 20006,
      "user": 8
    },
    "model": "user.usergroup",
    "pk": 20107
  },
  {
    "fields": {
      "default_group": 0,
      "group": 20003,
      "user": 8
    },
    "model": "user.usergroup",
    "pk": 20108
  },
  {
    "fields": {
      "default_group": 0,
      "group": 10000,
      "user": 8
    },
    "model": "user.usergroup",
    "pk": 20109
  },
  {
    "fields": {
      "city": "Geneva",
      "language": "en",
      "user": 2
    },
    "model": "user.usert",
    "pk": 1
  },
  {
    "fields": {
      "city": "Geneve",
      "language": "fr",
      "user": 2
    },
    "model": "user.usert",
    "pk": 2
  },
  {
    "fields": {
      "city": "Luzern",
      "language": "en",
      "user": 1
    },
    "model": "user.usert",
    "pk": 3
  },
  {
    "fields": {
      "city": "Lucerne",
      "language": "fr",
      "user": 1
    },
    "model": "user.usert",
    "pk": 4
  },
  {
    "fields": {
      "city": "Bern",
      "language": "en",
      "user": 8
    },
    "model": "user.usert",
    "pk": 5
  },
  {
    "fields": {
      "city": "Berne",
      "language": "fr",
      "user": 8
    },
    "model": "user.usert",
    "pk": 6
  }
]